<?xml version="1.0" ?>
<hierarchy rotation="0">
	<node index="0" text="" resource-id="" class="android.widget.FrameLayout" package="com.sh.shuihulu.kiwi" content-desc="" checkable="false" checked="false" clickable="false" enabled="true" focusable="false" focused="false" scrollable="false" long-clickable="false" password="false" selected="false" bounds="[0,72][1080,1920]">
		<node index="0" text="" resource-id="" class="android.widget.FrameLayout" package="com.sh.shuihulu.kiwi" content-desc="" checkable="false" checked="false" clickable="false" enabled="true" focusable="false" focused="false" scrollable="false" long-clickable="false" password="false" selected="false" bounds="[0,72][1080,1920]">
			<node index="0" text="" resource-id="android:id/content" class="android.widget.FrameLayout" package="com.sh.shuihulu.kiwi" content-desc="" checkable="false" checked="false" clickable="false" enabled="true" focusable="false" focused="false" scrollable="false" long-clickable="false" password="false" selected="false" bounds="[0,72][1080,1920]">
				<node index="0" text="" resource-id="" class="android.webkit.WebView" package="com.sh.shuihulu.kiwi" content-desc="" checkable="false" checked="false" clickable="false" enabled="true" focusable="false" focused="false" scrollable="false" long-clickable="false" password="false" selected="false" bounds="[0,72][1080,1920]">
					<node index="0" text="" resource-id="" class="android.webkit.WebView" package="com.sh.shuihulu.kiwi" content-desc="" checkable="false" checked="false" clickable="false" enabled="true" focusable="true" focused="true" scrollable="true" long-clickable="false" password="false" selected="false" bounds="[0,72][1080,1920]">
						<node index="0" text="" resource-id="" class="android.view.View" package="com.sh.shuihulu.kiwi" content-desc="" checkable="false" checked="false" clickable="true" enabled="true" focusable="false" focused="false" scrollable="false" long-clickable="false" password="false" selected="false" bounds="[0,72][1080,1920]">
							<node index="0" text="" resource-id="" class="android.view.View" package="com.sh.shuihulu.kiwi" content-desc="" checkable="false" checked="false" clickable="false" enabled="true" focusable="false" focused="false" scrollable="false" long-clickable="false" password="false" selected="false" bounds="[36,354][1044,1710]">
								<node index="0" text="" resource-id="" class="android.widget.Image" package="com.sh.shuihulu.kiwi" content-desc="" checkable="false" checked="false" clickable="false" enabled="true" focusable="false" focused="false" scrollable="false" long-clickable="false" password="false" selected="false" bounds="[342,534][759,621]"/>
								<node index="1" text="恭喜获得" resource-id="" class="android.view.View" package="com.sh.shuihulu.kiwi" content-desc="" checkable="false" checked="false" clickable="false" enabled="true" focusable="false" focused="false" scrollable="false" long-clickable="false" password="false" selected="false" bounds="[93,687][1011,735]"/>
								<node index="2" text="2元" resource-id="" class="android.view.View" package="com.sh.shuihulu.kiwi" content-desc="" checkable="false" checked="false" clickable="false" enabled="true" focusable="false" focused="false" scrollable="false" long-clickable="false" password="false" selected="false" bounds="[93,732][1011,915]"/>
								<node index="3" text="5元即可提现" resource-id="" class="android.view.View" package="com.sh.shuihulu.kiwi" content-desc="" checkable="false" checked="false" clickable="false" enabled="true" focusable="false" focused="false" scrollable="false" long-clickable="false" password="false" selected="false" bounds="[426,957][675,993]"/>
								<node index="4" text="" resource-id="" class="android.view.View" package="com.sh.shuihulu.kiwi" content-desc="" checkable="false" checked="false" clickable="false" enabled="true" focusable="false" focused="false" scrollable="false" long-clickable="false" password="false" selected="false" bounds="[93,1206][240,1266]">
									<node index="0" text="+0.6元" resource-id="" class="android.view.View" package="com.sh.shuihulu.kiwi" content-desc="" checkable="false" checked="false" clickable="false" enabled="true" focusable="false" focused="false" scrollable="false" long-clickable="false" password="false" selected="false" bounds="[123,1206][210,1245]"/>
								</node>
								<node index="5" text="" resource-id="" class="android.view.View" package="com.sh.shuihulu.kiwi" content-desc="" checkable="false" checked="false" clickable="false" enabled="true" focusable="false" focused="false" scrollable="false" long-clickable="false" password="false" selected="false" bounds="[138,1275][195,1329]">
									<node index="0" text="" resource-id="" class="android.view.View" package="com.sh.shuihulu.kiwi" content-desc="" checkable="false" checked="false" clickable="false" enabled="true" focusable="false" focused="false" scrollable="false" long-clickable="false" password="false" selected="false" bounds="[138,1275][195,1329]"/>
									<node index="1" text="" resource-id="" class="android.view.View" package="com.sh.shuihulu.kiwi" content-desc="" checkable="false" checked="false" clickable="false" enabled="true" focusable="false" focused="false" scrollable="false" long-clickable="false" password="false" selected="false" bounds="[138,1293][297,1311]"/>
								</node>
								<node index="6" text="完成注册" resource-id="" class="android.view.View" package="com.sh.shuihulu.kiwi" content-desc="" checkable="false" checked="false" clickable="false" enabled="true" focusable="false" focused="false" scrollable="false" long-clickable="false" password="false" selected="false" bounds="[105,1365][228,1401]"/>
								<node index="7" text="" resource-id="" class="android.view.View" package="com.sh.shuihulu.kiwi" content-desc="" checkable="false" checked="false" clickable="false" enabled="true" focusable="false" focused="false" scrollable="false" long-clickable="false" password="false" selected="false" bounds="[246,1206][393,1266]">
									<node index="0" text="+0.2元" resource-id="" class="android.view.View" package="com.sh.shuihulu.kiwi" content-desc="" checkable="false" checked="false" clickable="false" enabled="true" focusable="false" focused="false" scrollable="false" long-clickable="false" password="false" selected="false" bounds="[279,1206][363,1245]"/>
								</node>
								<node index="8" text="" resource-id="" class="android.view.View" package="com.sh.shuihulu.kiwi" content-desc="" checkable="false" checked="false" clickable="false" enabled="true" focusable="false" focused="false" scrollable="false" long-clickable="false" password="false" selected="false" bounds="[294,1275][348,1329]">
									<node index="0" text="" resource-id="" class="android.view.View" package="com.sh.shuihulu.kiwi" content-desc="" checkable="false" checked="false" clickable="false" enabled="true" focusable="false" focused="false" scrollable="false" long-clickable="false" password="false" selected="false" bounds="[294,1275][348,1329]"/>
									<node index="1" text="" resource-id="" class="android.view.View" package="com.sh.shuihulu.kiwi" content-desc="" checkable="false" checked="false" clickable="false" enabled="true" focusable="false" focused="false" scrollable="false" long-clickable="false" password="false" selected="false" bounds="[294,1293][450,1311]"/>
								</node>
								<node index="9" text="上传头像" resource-id="" class="android.view.View" package="com.sh.shuihulu.kiwi" content-desc="" checkable="false" checked="false" clickable="false" enabled="true" focusable="false" focused="false" scrollable="false" long-clickable="false" password="false" selected="false" bounds="[258,1365][384,1401]"/>
								<node index="10" text="" resource-id="" class="android.view.View" package="com.sh.shuihulu.kiwi" content-desc="" checkable="false" checked="false" clickable="false" enabled="true" focusable="false" focused="false" scrollable="false" long-clickable="false" password="false" selected="false" bounds="[402,1206][549,1266]">
									<node index="0" text="+0.8元" resource-id="" class="android.view.View" package="com.sh.shuihulu.kiwi" content-desc="" checkable="false" checked="false" clickable="false" enabled="true" focusable="false" focused="false" scrollable="false" long-clickable="false" password="false" selected="false" bounds="[432,1206][516,1245]"/>
								</node>
								<node index="11" text="" resource-id="" class="android.view.View" package="com.sh.shuihulu.kiwi" content-desc="" checkable="false" checked="false" clickable="false" enabled="true" focusable="false" focused="false" scrollable="false" long-clickable="false" password="false" selected="false" bounds="[447,1275][501,1329]">
									<node index="0" text="" resource-id="" class="android.view.View" package="com.sh.shuihulu.kiwi" content-desc="" checkable="false" checked="false" clickable="false" enabled="true" focusable="false" focused="false" scrollable="false" long-clickable="false" password="false" selected="false" bounds="[447,1275][501,1329]"/>
									<node index="1" text="" resource-id="" class="android.view.View" package="com.sh.shuihulu.kiwi" content-desc="" checkable="false" checked="false" clickable="false" enabled="true" focusable="false" focused="false" scrollable="false" long-clickable="false" password="false" selected="false" bounds="[447,1293][603,1311]"/>
								</node>
								<node index="12" text="真人认证" resource-id="" class="android.view.View" package="com.sh.shuihulu.kiwi" content-desc="" checkable="false" checked="false" clickable="false" enabled="true" focusable="false" focused="false" scrollable="false" long-clickable="false" password="false" selected="false" bounds="[411,1365][537,1401]"/>
								<node index="13" text="" resource-id="" class="android.view.View" package="com.sh.shuihulu.kiwi" content-desc="" checkable="false" checked="false" clickable="false" enabled="true" focusable="false" focused="false" scrollable="false" long-clickable="false" password="false" selected="false" bounds="[555,1206][702,1266]">
									<node index="0" text="+0.3元" resource-id="" class="android.view.View" package="com.sh.shuihulu.kiwi" content-desc="" checkable="false" checked="false" clickable="false" enabled="true" focusable="false" focused="false" scrollable="false" long-clickable="false" password="false" selected="false" bounds="[585,1206][672,1245]"/>
								</node>
								<node index="14" text="" resource-id="" class="android.view.View" package="com.sh.shuihulu.kiwi" content-desc="" checkable="false" checked="false" clickable="false" enabled="true" focusable="false" focused="false" scrollable="false" long-clickable="false" password="false" selected="false" bounds="[600,1275][657,1329]">
									<node index="0" text="" resource-id="" class="android.view.View" package="com.sh.shuihulu.kiwi" content-desc="" checkable="false" checked="false" clickable="false" enabled="true" focusable="false" focused="false" scrollable="false" long-clickable="false" password="false" selected="false" bounds="[600,1275][657,1329]"/>
									<node index="1" text="" resource-id="" class="android.view.View" package="com.sh.shuihulu.kiwi" content-desc="" checkable="false" checked="false" clickable="false" enabled="true" focusable="false" focused="false" scrollable="false" long-clickable="false" password="false" selected="false" bounds="[600,1293][759,1311]"/>
								</node>
								<node index="15" text="交友宣言" resource-id="" class="android.view.View" package="com.sh.shuihulu.kiwi" content-desc="" checkable="false" checked="false" clickable="false" enabled="true" focusable="false" focused="false" scrollable="false" long-clickable="false" password="false" selected="false" bounds="[567,1365][690,1401]"/>
								<node index="16" text="" resource-id="" class="android.view.View" package="com.sh.shuihulu.kiwi" content-desc="" checkable="false" checked="false" clickable="false" enabled="true" focusable="false" focused="false" scrollable="false" long-clickable="false" password="false" selected="false" bounds="[708,1206][855,1266]">
									<node index="0" text="+0.1元" resource-id="" class="android.view.View" package="com.sh.shuihulu.kiwi" content-desc="" checkable="false" checked="false" clickable="false" enabled="true" focusable="false" focused="false" scrollable="false" long-clickable="false" password="false" selected="false" bounds="[741,1206][825,1245]"/>
								</node>
								<node index="17" text="" resource-id="" class="android.view.View" package="com.sh.shuihulu.kiwi" content-desc="" checkable="false" checked="false" clickable="false" enabled="true" focusable="false" focused="false" scrollable="false" long-clickable="false" password="false" selected="false" bounds="[756,1275][810,1329]">
									<node index="0" text="" resource-id="" class="android.view.View" package="com.sh.shuihulu.kiwi" content-desc="" checkable="false" checked="false" clickable="false" enabled="true" focusable="false" focused="false" scrollable="false" long-clickable="false" password="false" selected="false" bounds="[756,1275][810,1329]"/>
									<node index="1" text="" resource-id="" class="android.view.View" package="com.sh.shuihulu.kiwi" content-desc="" checkable="false" checked="false" clickable="false" enabled="true" focusable="false" focused="false" scrollable="false" long-clickable="false" password="false" selected="false" bounds="[756,1293][912,1311]"/>
								</node>
								<node index="18" text="填写昵称" resource-id="" class="android.view.View" package="com.sh.shuihulu.kiwi" content-desc="" checkable="false" checked="false" clickable="false" enabled="true" focusable="false" focused="false" scrollable="false" long-clickable="false" password="false" selected="false" bounds="[720,1365][846,1401]"/>
								<node index="19" text="" resource-id="" class="android.view.View" package="com.sh.shuihulu.kiwi" content-desc="" checkable="false" checked="false" clickable="false" enabled="true" focusable="false" focused="false" scrollable="false" long-clickable="false" password="false" selected="false" bounds="[864,1206][1011,1266]">
									<node index="0" text="+0.4元" resource-id="" class="android.view.View" package="com.sh.shuihulu.kiwi" content-desc="" checkable="false" checked="false" clickable="false" enabled="true" focusable="false" focused="false" scrollable="false" long-clickable="false" password="false" selected="false" bounds="[894,1206][978,1245]"/>
								</node>
								<node index="20" text="" resource-id="" class="android.view.View" package="com.sh.shuihulu.kiwi" content-desc="" checkable="false" checked="false" clickable="false" enabled="true" focusable="false" focused="false" scrollable="false" long-clickable="false" password="false" selected="false" bounds="[909,1275][963,1329]">
									<node index="0" text="" resource-id="" class="android.view.View" package="com.sh.shuihulu.kiwi" content-desc="" checkable="false" checked="false" clickable="false" enabled="true" focusable="false" focused="false" scrollable="false" long-clickable="false" password="false" selected="false" bounds="[909,1275][963,1329]"/>
								</node>
								<node index="21" text="完善资料和相册" resource-id="" class="android.view.View" package="com.sh.shuihulu.kiwi" content-desc="" checkable="false" checked="false" clickable="false" enabled="true" focusable="false" focused="false" scrollable="false" long-clickable="false" password="false" selected="false" bounds="[873,1368][999,1440]"/>
								<node index="22" text="" resource-id="" class="android.view.View" package="com.sh.shuihulu.kiwi" content-desc="" checkable="false" checked="false" clickable="true" enabled="true" focusable="false" focused="false" scrollable="false" long-clickable="false" password="false" selected="false" bounds="[216,1482][888,1611]">
									<node index="0" text="去完善资料和相册" resource-id="" class="android.view.View" package="com.sh.shuihulu.kiwi" content-desc="" checkable="false" checked="false" clickable="false" enabled="true" focusable="false" focused="false" scrollable="false" long-clickable="false" password="false" selected="false" bounds="[354,1494][747,1554]"/>
									<node index="1" text="(+0.4元)" resource-id="" class="android.view.View" package="com.sh.shuihulu.kiwi" content-desc="" checkable="false" checked="false" clickable="false" enabled="true" focusable="false" focused="false" scrollable="false" long-clickable="false" password="false" selected="false" bounds="[315,1554][786,1590]"/>
								</node>
							</node>
						</node>
					</node>
				</node>
			</node>
		</node>
	</node>
</hierarchy>
