<?xml version="1.0" ?>
<hierarchy rotation="0">
	<node index="0" text="" resource-id="" class="android.widget.FrameLayout" package="com.dd.rclient" content-desc="" checkable="false" checked="false" clickable="false" enabled="true" focusable="false" focused="false" scrollable="false" long-clickable="false" password="false" selected="false" bounds="[0,0][1080,1920]">
		<node index="0" text="" resource-id="" class="android.widget.LinearLayout" package="com.dd.rclient" content-desc="" checkable="false" checked="false" clickable="false" enabled="true" focusable="false" focused="false" scrollable="false" long-clickable="false" password="false" selected="false" bounds="[0,0][1080,1920]">
			<node index="0" text="" resource-id="" class="android.widget.FrameLayout" package="com.dd.rclient" content-desc="" checkable="false" checked="false" clickable="false" enabled="true" focusable="false" focused="false" scrollable="false" long-clickable="false" password="false" selected="false" bounds="[0,0][1080,1920]">
				<node index="0" text="" resource-id="com.dd.rclient:id/action_bar_root" class="android.widget.LinearLayout" package="com.dd.rclient" content-desc="" checkable="false" checked="false" clickable="false" enabled="true" focusable="false" focused="false" scrollable="false" long-clickable="false" password="false" selected="false" bounds="[0,0][1080,1920]">
					<node index="0" text="" resource-id="android:id/content" class="android.widget.FrameLayout" package="com.dd.rclient" content-desc="" checkable="false" checked="false" clickable="false" enabled="true" focusable="false" focused="false" scrollable="false" long-clickable="false" password="false" selected="false" bounds="[0,0][1080,1920]">
						<node index="0" text="" resource-id="" class="android.view.ViewGroup" package="com.dd.rclient" content-desc="" checkable="false" checked="false" clickable="false" enabled="true" focusable="false" focused="false" scrollable="false" long-clickable="false" password="false" selected="false" bounds="[0,0][1080,1920]">
							<node index="0" text="" resource-id="com.dd.rclient:id/title_bar" class="android.widget.LinearLayout" package="com.dd.rclient" content-desc="" checkable="false" checked="false" clickable="false" enabled="true" focusable="false" focused="false" scrollable="false" long-clickable="false" password="false" selected="false" bounds="[0,0][1080,240]">
								<node index="0" text="" resource-id="" class="android.widget.RelativeLayout" package="com.dd.rclient" content-desc="" checkable="false" checked="false" clickable="false" enabled="true" focusable="false" focused="false" scrollable="false" long-clickable="false" password="false" selected="false" bounds="[0,72][1080,240]">
									<node index="0" text="吴智勇" resource-id="com.dd.rclient:id/now_login_account" class="android.widget.TextView" package="com.dd.rclient" content-desc="" checkable="false" checked="false" clickable="false" enabled="true" focusable="false" focused="false" scrollable="false" long-clickable="false" password="false" selected="false" bounds="[0,72][240,240]"/>
									<node index="1" text="" resource-id="com.dd.rclient:id/change_account_btn" class="android.widget.ImageView" package="com.dd.rclient" content-desc="icon" checkable="false" checked="false" clickable="true" enabled="true" focusable="false" focused="false" scrollable="false" long-clickable="false" password="false" selected="false" bounds="[909,72][1080,240]"/>
								</node>
							</node>
							<node NAF="true" index="1" text="" resource-id="com.dd.rclient:id/auto_wait_btn" class="android.view.View" package="com.dd.rclient" content-desc="" checkable="false" checked="false" clickable="true" enabled="true" focusable="false" focused="false" scrollable="false" long-clickable="false" password="false" selected="false" bounds="[240,384][840,984]"/>
							<node index="3" text="退出程序" resource-id="com.dd.rclient:id/btn_exit_app" class="android.widget.TextView" package="com.dd.rclient" content-desc="" checkable="false" checked="false" clickable="true" enabled="true" focusable="false" focused="false" scrollable="false" long-clickable="false" password="false" selected="false" bounds="[104,1349][488,1474]"/>
							<node index="4" text="后台运行" resource-id="com.dd.rclient:id/btn_run_on_background" class="android.widget.TextView" package="com.dd.rclient" content-desc="" checkable="false" checked="false" clickable="true" enabled="true" focusable="false" focused="false" scrollable="false" long-clickable="false" password="false" selected="false" bounds="[592,1349][976,1474]"/>
							<node index="5" text="注意事项: 

1.当APP处于挂机状态时请将此页面至于最前端.
2.请将此APP添加至锁屏清理白名单以避免息屏掉线.
3.当前设备中如有重要隐私应用或数据请使用应用锁.
4.请保证挂机设备处于良好的网络条件中." resource-id="com.dd.rclient:id/info_text" class="android.widget.TextView" package="com.dd.rclient" content-desc="" checkable="false" checked="false" clickable="false" enabled="true" focusable="false" focused="false" scrollable="false" long-clickable="false" password="false" selected="false" bounds="[48,1570][1032,1872]"/>
						</node>
					</node>
				</node>
			</node>
		</node>
	</node>
</hierarchy>
